codespan_reporting-0.1.0.dist-info/METADATA
codespan_reporting-0.1.0.dist-info/WHEEL
codespan_reporting-0.1.0.dist-info/license_files/LICENSE
codespan_reporting/__init__.py
codespan_reporting/_core.pyi
codespan_reporting/_core.cpython-312-x86_64-linux-gnu.so
codespan_reporting-0.1.0.dist-info/RECORD
