Metadata-Version: 2.1
Name: codespan-reporting
Version: 0.1.0
Classifier: License :: OSI Approved :: MIT License
Classifier: Programming Language :: Rust
Classifier: Programming Language :: Python
Classifier: Programming Language :: Python :: 3
Classifier: Programming Language :: Python :: 3.9
Classifier: Programming Language :: Python :: 3.10
Classifier: Programming Language :: Python :: 3.11
Classifier: Programming Language :: Python :: 3.12
Classifier: Programming Language :: Python :: Implementation :: CPython
Classifier: Programming Language :: Python :: Implementation :: PyPy
Requires-Dist: pytest >=7.4.4 ; extra == 'dev'
Requires-Dist: ruff ==0.1.14 ; extra == 'dev'
Requires-Dist: pyright >=1.1.293 ; extra == 'dev'
Requires-Dist: build ; extra == 'dev'
Provides-Extra: dev
License-File: LICENSE
Summary: A python binding for codespan-reporting
Keywords: codespan-reporting
Author-email: Nyakku Shigure <sigure.qaq@gmail.com>
License: MIT
Requires-Python: >=3.8
